kanjiconv/__init__.py
kanjiconv/data/kana.json
kanjiconv/data/kanji_readings.json
kanjiconv/entities/__init__.py
kanjiconv/entities/sudachi_dict.py
kanjiconv/kanjiconv.py
kanjiconv/post_install.py
kanjiconv-0.2.4.dist-info/LICENSE
kanjiconv-0.2.4.dist-info/METADATA
kanjiconv-0.2.4.dist-info/WHEEL
kanjiconv-0.2.4.dist-info/entry_points.txt
kanjiconv-0.2.4.dist-info/RECORD
