Metadata-Version: 2.3
Name: kanjiconv
Version: 0.2.4
Summary: Kanji Converter to Hiragana, Katakana, Roman alphabet
License: Apache-2.0
Keywords: kanji,kana,converter,sudachi,propernoun
Author: sea-turt1e
Author-email: h.yamada.bg@gmail.com
Requires-Python: >=3.11,<4.0
Classifier: License :: OSI Approved :: Apache Software License
Classifier: Programming Language :: Python :: 3
Classifier: Programming Language :: Python :: 3.11
Classifier: Programming Language :: Python :: 3.12
Classifier: Programming Language :: Python :: 3.13
Requires-Dist: fugashi (>=1.4.0,<2.0.0)
Requires-Dist: sudachidict-full
Requires-Dist: sudachipy (>=0.6.8)
Requires-Dist: unidic (>=1.1.0,<2.0.0)
Project-URL: Repository, https://github.com/sea-turt1e/kanjiconv
